pyflet/__init__.py
pyflet/main.py
pyflet-0.3.0.dist-info/LICENCE
pyflet-0.3.0.dist-info/METADATA
pyflet-0.3.0.dist-info/WHEEL
pyflet-0.3.0.dist-info/entry_points.txt
pyflet-0.3.0.dist-info/top_level.txt
pyflet-0.3.0.dist-info/RECORD
