Metadata-Version: 2.2
Name: pyflet
Version: 0.3.0
Summary: A CLI tool for generating and managing web projects using Flet.
Home-page: https://github.com/webtechmoz/pyflet
Author: DevPythonMZ
Author-email: zoidycine@egmail.com
Classifier: Programming Language :: Python :: 3
Classifier: License :: OSI Approved :: MIT License
Classifier: Operating System :: OS Independent
Requires-Python: >=3.6
License-File: LICENCE
Requires-Dist: typer
Requires-Dist: manage.sql
Dynamic: author
Dynamic: author-email
Dynamic: classifier
Dynamic: description
Dynamic: description-content-type
Dynamic: home-page
Dynamic: requires-dist
Dynamic: requires-python
Dynamic: summary
